flask_captcha2/CaptchaClass.py
flask_captcha2/Logger.py
flask_captcha2/__init__.py
flask_captcha2/excep.py
flask_captcha2/GoogleCaptcha/__init__.py
flask_captcha2/GoogleCaptcha/captcha2.py
flask_captcha2/GoogleCaptcha/captcha3.py
flask_captcha2/GoogleCaptcha/utils.py
flask_captcha2/LocalCaptcha/__init__.py
flask_captcha2/LocalCaptcha/Image/__init__.py
flask_captcha2/LocalCaptcha/Image/img.py
flask_captcha2/LocalCaptcha/Voice/__init__.py
tests/__init__.py
tests/conftest.py
Flask_captcha2-3.1.0.dist-info/LICENSE
Flask_captcha2-3.1.0.dist-info/METADATA
Flask_captcha2-3.1.0.dist-info/WHEEL
Flask_captcha2-3.1.0.dist-info/top_level.txt
Flask_captcha2-3.1.0.dist-info/RECORD
