Metadata-Version: 2.1
Name: Flask-captcha2
Version: 3.1.0
Summary: Flask plugin to integrate Google captcha (version 2, 3) and local captcha (image, voice) with Flask applications
Home-page: https://github.com/alisharify7/flask_captcha2
Author: ali sharify
Author-email: alisharifyofficial@gmail.com
License: MIT
Keywords: flask security,Google captcha for flask,captcha,flask,flask-captcha,flask-captcha2,flask_captcha2,flask-images-captcha
Classifier: License :: OSI Approved :: MIT License
Classifier: Operating System :: OS Independent
Classifier: Programming Language :: Python
Classifier: Programming Language :: Python :: 3.8
Classifier: Programming Language :: Python :: 3.9
Classifier: Programming Language :: Python :: 3.10
Classifier: Programming Language :: Python :: 3.11
Classifier: Programming Language :: Python :: 3.12
Classifier: Environment :: Web Environment
Classifier: Topic :: Security
Classifier: Topic :: Internet :: WWW/HTTP
Classifier: Framework :: Flask
Requires-Python: >=3.8
License-File: LICENSE
Requires-Dist: flask >=2.2.5
Requires-Dist: markupsafe >=2.1.2
Requires-Dist: requests >=2.30.0
Requires-Dist: captcha >=0.5.0
